llms_wrapper/__init__.py
llms_wrapper/chatbot.py
llms_wrapper/config.py
llms_wrapper/llms.py
llms_wrapper/llms_wrapper_llminfo.py
llms_wrapper/llms_wrapper_test.py
llms_wrapper/llms_wrapper_webchat.py
llms_wrapper/log.py
llms_wrapper/model_list.py
llms_wrapper/utils.py
llms_wrapper/utils_loguru.py
llms_wrapper/version.py
llms_wrapper-0.7.dist-info/licenses/LICENSE
llms_wrapper-0.7.dist-info/METADATA
llms_wrapper-0.7.dist-info/WHEEL
llms_wrapper-0.7.dist-info/entry_points.txt
llms_wrapper-0.7.dist-info/top_level.txt
llms_wrapper-0.7.dist-info/RECORD
